{
  "dateHighlightedFormat": "yyyy-MM-dd HH:mm:ss",
  "dateSavedFormat": "yyyy-MM-dd HH:mm:ss",
  "apiKey": "e6bea3e6-2d4b-4fdf-a27f-5131a26b23f6",
  "filter": "HIGHLIGHTS",
  "syncAt": "2025-01-19T06:34:21",
  "customQuery": "in:all has:highlights mode:highlights",
  "template": "# {{{title}}}\n#Omnivore\n\n[Read on Omnivore]({{{omnivoreUrl}}})\n[Read Original]({{{originalUrl}}})\n\n{{#highlights.length}}\n## Highlights\n\n{{#highlights}}\n> {{{text}}} [⤴️]({{{highlightUrl}}}) {{#labels}} #{{name}} {{/labels}} \n{{#note}}\n\n{{{note}}}\n{{/note}}\n\n{{/highlights}}\n{{/highlights.length}}",
  "highlightOrder": "LOCATION",
  "syncing": false,
  "folder": "Omnivore/{{{date}}}",
  "folderDateFormat": "yyyy-MM-dd",
  "endpoint": "https://api-prod.omnivore.app/api/graphql",
  "filename": "{{{title}}}",
  "filenameDateFormat": "yyyy-MM-dd",
  "attachmentFolder": "Omnivore/attachments",
  "version": "1.10.4",
  "isSingleFile": false,
  "frequency": 0,
  "intervalId": 0,
  "frontMatterVariables": [],
  "frontMatterTemplate": "",
  "syncOnStart": true,
  "enableHighlightColorRender": false,
  "highlightManagerId": "omni",
  "highlightColorMapping": {
    "yellow": "#fff3a3",
    "red": "#ff5582",
    "blue": "#adccff",
    "green": "#bbfabb"
  }
}